pygribjump/__init__.py
pygribjump/_version.py
pygribjump/gribjump_c.h
pygribjump/pygribjump.py
pygribjump-0.10.3.9.dist-info/licenses/LICENSE
pygribjump-0.10.3.9.dist-info/METADATA
pygribjump-0.10.3.9.dist-info/WHEEL
pygribjump-0.10.3.9.dist-info/top_level.txt
pygribjump-0.10.3.9.dist-info/RECORD
