Metadata-Version: 2.4
Name: pygribjump
Version: 0.10.3.9
Summary: Python interface to GribJump
Author-email: ECMWF <software.support@ecmwf.int>
License-Expression: Apache-2.0
Project-URL: Home, https://github.com/ecmwf/gribjump
Requires-Python: >=3.9
License-File: LICENSE
Requires-Dist: cffi~=1.17
Requires-Dist: numpy>=1.26
Requires-Dist: findlibs>=0.1.1
Requires-Dist: packaging>=20.0
Provides-Extra: dev
Requires-Dist: pytest>=8.3; extra == "dev"
Requires-Dist: pyyaml; extra == "dev"
Requires-Dist: pyfdb; extra == "dev"
Dynamic: license-file
